alia/__init__.py
alia/colors.py
alia/df_tools.py
alia/tools.py
alia-0.2.11.dist-info/LICENSE
alia-0.2.11.dist-info/METADATA
alia-0.2.11.dist-info/WHEEL
alia-0.2.11.dist-info/top_level.txt
alia-0.2.11.dist-info/RECORD
