Metadata-Version: 2.1
Name: alia
Version: 0.2.11
Summary: A collection of random helper tools to make life easier
Home-page: https://github.com/aliavictor/alia
Author: Alia
Author-email: alia.jo.victor@gmail.com
Classifier: Development Status :: 3 - Alpha
Classifier: Intended Audience :: Developers
Classifier: License :: OSI Approved :: MIT License
Classifier: Programming Language :: Python :: 3
Classifier: Programming Language :: Python :: 3.7
Classifier: Programming Language :: Python :: 3.8
Classifier: Programming Language :: Python :: 3.9
License-File: LICENSE
Requires-Dist: numpy
Requires-Dist: pandas
Requires-Dist: requests
Requires-Dist: python-dotenv
Requires-Dist: sty
Requires-Dist: pyperclip
Requires-Dist: python-dateutil
Requires-Dist: ipython
Requires-Dist: fernet
Requires-Dist: cryptography
